urarovite/__init__.py
urarovite/__main__.py
urarovite/_version.py
urarovite/cli.py
urarovite/cli_base.py
urarovite/cli_utils.py
urarovite/auth/__init__.py
urarovite/auth/google_drive.py
urarovite/auth/google_sheets.py
urarovite/config/__init__.py
urarovite/config/validation_criteria.py
urarovite/core/__init__.py
urarovite/core/api.py
urarovite/core/exceptions.py
urarovite/core/local_excel_optimizer.py
urarovite/core/smart_chunking_optimizer.py
urarovite/core/spreadsheet.py
urarovite/core/spreadsheet_excel.py
urarovite/core/spreadsheet_google.py
urarovite/resolver/__init__.py
urarovite/utils/README.md
urarovite/utils/__init__.py
urarovite/utils/a1_range_validator.py
urarovite/utils/cell_value_validation_utility.py
urarovite/utils/comprehensive_formatting.py
urarovite/utils/drive.py
urarovite/utils/enhanced_conversion.py
urarovite/utils/format_preservation.py
urarovite/utils/formula_aware_conversion.py
urarovite/utils/forte_processing.py
urarovite/utils/generic_spreadsheet copy.py
urarovite/utils/generic_spreadsheet.py
urarovite/utils/google_api_backoff.py
urarovite/utils/native_excel_import.py
urarovite/utils/open_ended_ranges_util.py
urarovite/utils/progress.py
urarovite/utils/sheets.py
urarovite/utils/simple_converter.py
urarovite/utils/tab_name_sanitizer.py
urarovite/utils/tab_renamer.py
urarovite/validators/__init__.py
urarovite/validators/attached_files_cleaner.py
urarovite/validators/base.py
urarovite/validators/broken_values.py
urarovite/validators/bulk_rename_spreadsheets.py
urarovite/validators/case_sensitivity_hint.py
urarovite/validators/cell_value_validation.py
urarovite/validators/csv_to_json_transform.py
urarovite/validators/data_quality.py
urarovite/validators/data_quality_updated.py
urarovite/validators/different_within_ranges.py
urarovite/validators/duplicate_overlapping_ranges.py
urarovite/validators/empty_invalid_ranges.py
urarovite/validators/fixed_verification_ranges.py
urarovite/validators/format_compatibility.py
urarovite-1.3.4.dist-info/METADATA
urarovite-1.3.4.dist-info/WHEEL
urarovite-1.3.4.dist-info/entry_points.txt
urarovite-1.3.4.dist-info/licenses/LICENSE
urarovite-1.3.4.dist-info/RECORD
