Metadata-Version: 2.4
Name: urarovite
Version: 1.3.4
Summary: A Google Sheets validation library
Project-URL: Homepage, https://github.com/ParetoWorkers/Urarovite
Project-URL: Documentation, https://github.com/ParetoWorkers/Urarovite#readme
Project-URL: Repository, https://github.com/ParetoWorkers/Urarovite.git
Project-URL: flags, https://github.com/ParetoWorkers/Urarovite/flags
Project-URL: Changelog, https://github.com/ParetoWorkers/Urarovite/blob/main/MIGRATION_SUMMARY.md
Author-email: Mo Dorff <mohonrid@gmail.com>
License: GNU GENERAL PUBLIC LICENSE
License-File: LICENSE
Keywords: data-quality,google-sheets,gspread,spreadsheets,validation
Classifier: Development Status :: 4 - Beta
Classifier: Intended Audience :: Developers
Classifier: License :: OSI Approved :: GNU General Public License v3 (GPLv3)
Classifier: Operating System :: OS Independent
Classifier: Programming Language :: Python :: 3
Classifier: Programming Language :: Python :: 3.9
Classifier: Programming Language :: Python :: 3.10
Classifier: Programming Language :: Python :: 3.11
Classifier: Programming Language :: Python :: 3.12
Classifier: Programming Language :: Python :: 3.13
Classifier: Topic :: Internet :: WWW/HTTP :: Dynamic Content
Classifier: Topic :: Office/Business :: Office Suites
Classifier: Topic :: Software Development :: Libraries :: Python Modules
Requires-Python: >=3.9
Requires-Dist: google-api-python-client>=2.0.0
Requires-Dist: google-auth-httplib2>=0.2.0
Requires-Dist: google-auth-oauthlib>=1.0.0
Requires-Dist: google-auth>=2.0.0
Requires-Dist: gspread>=6.0.0
Requires-Dist: numpy>=1.20.0
Requires-Dist: openpyxl>=3.1.5
Requires-Dist: pandas>=1.5.0
Requires-Dist: python-dotenv>=1.1.1
Requires-Dist: requests>=2.25.0
Requires-Dist: rich>=13.0.0
Provides-Extra: dev
Requires-Dist: bandit[toml]>=1.7.5; extra == 'dev'
Requires-Dist: pre-commit>=3.6.0; extra == 'dev'
Requires-Dist: pydocstyle>=6.3.0; extra == 'dev'
Requires-Dist: pytest-cov>=4.0.0; extra == 'dev'
Requires-Dist: pytest>=8.0.0; extra == 'dev'
Requires-Dist: ruff>=0.9.6; extra == 'dev'
Provides-Extra: excel
Requires-Dist: openpyxl>=3.0.0; extra == 'excel'
Provides-Extra: notebook
Requires-Dist: ipykernel>=6.30.1; extra == 'notebook'
